{
    "portfolio": [
        {
            "id": 1,
            "img": "assets/img/laundry.jpg",
            "project": "Self Order Restaurant",
            "description": "Web responsive for booking food, beverage & dessert",
            "link": "#",
            "tahun": "ongoing",
            "backend": "Rest API DB Progress",
            "version": "web"
        },
        {
            "id": 2,
            "img": "https://source.unsplash.com/random/500x500",
            "project": "Web Akusara Law Office",
            "description": "Web company profile",
            "link": "http://akusaralawoffice.com",
            "tahun": "2021",
            "backend": "",
            "version": "web"
        },
        {
            "id": 3,
            "img": "assets/img/laundry.jpg",
            "project": "XX One Cinema",
            "description": "Cinema ticket booking simulation application using the flutter framework",
            "link": "https://github.com/cybanjar",
            "tahun": "2021",
            "backend": "Firebase",
            "version": "mobile android"
        },
        {
            "id": 4,
            "img": "assets/img/laundry.jpg",
            "project": "Self Checkin Hotel",
            "description": "Self checkin for hotel, precheckin - checkin",
            "link": "http://vhp-online.com",
            "tahun": "2020",
            "backend": "Rest API DB Progress",
            "version": "web"
        },
        {
            "id": 5,
            "img": "assets/img/laundry.jpg",
            "project": "Mengaji",
            "description": "Quran online",
            "link": "https://my-project-dumet.web.app",
            "tahun": "2020",
            "backend": "Firebase",
            "version": "web"
        },
        {
            "id": 6,
            "img": "https://source.unsplash.com/random/500x500",
            "project": "Invite Wedding",
            "description": "Invitation wedding",
            "link": "https://wedding-vika.web.app/welcome-vika",
            "tahun": "2020",
            "backend": "Firebase",
            "version": "web"
        },
        {
            "id": 7,
            "img": "assets/img/laundry.jpg",
            "project": "VHP Web",
            "description": "Visual Hotel Program for hotel",
            "link": "http://vue.e1-vhp.com:8080",
            "tahun": "2020",
            "backend": "Rest API DB Progress",
            "version": "web"
        },
        {
            "id": 8,
            "img": "assets/img/laundry.jpg",
            "project": "Helpdesk",
            "description": "For helpdesk client request or bug fixing",
            "link": "http://devhdesk.e1-vhp.com",
            "tahun": "2021",
            "backend": "Rest API DB Progress",
            "version": "web"
        },
        {
            "id": 9,
            "img": "assets/img/laundry.jpg",
            "project": "New DB Setup",
            "description": "For setup VHP Web",
            "link": "#",
            "tahun": "2020",
            "backend": "",
            "version": "UI Design figma"
        },
        {
            "id": 10,
            "img": "assets/img/laundry.jpg",
            "project": "Web PT. Indo Cahaya Wira Nusantara",
            "description": "Web company profile PT.ICWN",
            "link": "http://icwn.co.id",
            "tahun": "2019",
            "backend": "PHP",
            "version": "Web"
        },
        {
            "id": 11,
            "img": "assets/img/laundry.jpg",
            "project": "Web PT. Gemilang Mahakarya Pramata",
            "description": "Web company profile PT.GMP",
            "link": "http://mahakaryapratama.com",
            "tahun": "2019",
            "backend": "",
            "version": "Web"
        },
        {
            "id": 12,
            "img": "assets/img/laundry.jpg",
            "project": "Web Laundry",
            "description": "Web application laundry",
            "link": "#",
            "tahun": "2018",
            "backend": "PHP MYSQL",
            "version": "Web"
        },
        {
            "id": 13,
            "img": "assets/img/laundry.jpg",
            "project": "HR Management Orange HRM",
            "description": "Human Resource Management | failed project",
            "link": "#",
            "tahun": "2018",
            "backend": "PHP MYSQL",
            "version": "Web"
        },
        {
            "id": 14,
            "img": "assets/img/laundry.jpg",
            "project": "Build internal server",
            "description": "For HRM",
            "link": "#",
            "tahun": "2018",
            "backend": "",
            "version": "Ubuntu Server"
        },
        {
            "id": 15,
            "img": "assets/img/laundry.jpg",
            "project": "Build Turnkey File Server",
            "description": "File server internal office",
            "link": "#",
            "tahun": "2017",
            "backend": "",
            "version": "Turnkey file server"
        },
        {
            "id": 16,
            "img": "assets/img/laundry.jpg",
            "project": "e-arsip",
            "description": "arsip letter out and in for goverment",
            "link": "#",
            "tahun": "2017",
            "backend": "",
            "version": "Turnkey file server"
        }
    ],
    "education": [
        {
            "id": 1,
            "edu": "Flutter Developer",
            "tahun": "2021",
            "jurusan": "Mobile Development",
            "detailed": ""
        },
        {
            "id": 2,
            "edu": "Vue Js",
            "tahun": "2021",
            "jurusan": "Frontend Development",
            "detailed": ""
        },
        {
            "id": 3,
            "edu": "PHP & MySQL",
            "tahun": "2019",
            "jurusan": "Web Development",
            "detailed": ""
        },
        {
            "id": 20,
            "edu": "Bachelor of computer science",
            "tahun": "2015",
            "jurusan": "UPN Veteran Jakarta",
            "detailed": ""
        },
        {
            "id": 4,
            "edu": "Conversation",
            "tahun": "2015",
            "jurusan": "Speaking",
            "detailed": ""
        },
        {
            "id": 5,
            "edu": "TOEFL",
            "tahun": "2015",
            "jurusan": "Foreign language",
            "detailed": ""
        },
        {
            "id": 6,
            "edu": "Ethical Hacking",
            "tahun": "2014",
            "jurusan": "Security Computer",
            "detailed": ""
        },
        {
            "id": 7,
            "edu": "The world of hacking",
            "tahun": "2013",
            "jurusan": "Security Computer",
            "detailed": ""
        },
        {
            "id": 8,
            "edu": "Security cloud computing",
            "tahun": "2013",
            "jurusan": "Security Computer",
            "detailed": ""
        },
        {
            "id": 9,
            "edu": "Green IT cloud computing",
            "tahun": "2013",
            "jurusan": "Security Computer",
            "detailed": ""
        },
        {
            "id": 10,
            "edu": "Microsoft office 2013",
            "tahun": "2010",
            "jurusan": "Microfot office",
            "detailed": ""
        },
        {
            "id": 11,
            "edu": "Technician Computer",
            "tahun": "2010",
            "jurusan": "Maintenance computer",
            "detailed": ""
        },
        {
            "id": 12,
            "edu": "Microsoft access 2003",
            "tahun": "2009",
            "jurusan": "Microsoft office",
            "detailed": ""
        }
    ],
    "experience": [
        {
            "id": 1,
            "job_position": "Web Designer",
            "company_name": "PT. Sindata",
            "organization_name": "Research & Development",
            "job_level": "Staff",
            "employe_status": "permanent",
            "period": "01-10-2019",
            "description": "Development UI design, Web design, Alternative design for project Visual Hotel Program."
        }
    ]
}